pag/__init__.py
pag/classes.py
pag/game.py
pag/parser.py
pag/utils.py
pag/words.py
pag/dictionary/directions.txt
pag/dictionary/extras.txt
pag/dictionary/nouns.txt
pag/dictionary/verbs.txt
python_adventure_game-0.1.1.dist-info/DESCRIPTION.rst
python_adventure_game-0.1.1.dist-info/METADATA
python_adventure_game-0.1.1.dist-info/RECORD
python_adventure_game-0.1.1.dist-info/WHEEL
python_adventure_game-0.1.1.dist-info/metadata.json
python_adventure_game-0.1.1.dist-info/top_level.txt
