Metadata-Version: 2.0
Name: python-adventure-game
Version: 0.1.1
Summary: A simple text-based adventure game engine.
Home-page: https://github.com/allanburleson/python-adventure-game
Author: Allan Burleson
Author-email: burleson.a@icloud.com
License: MIT
Keywords: game text text-based adventure interactive-fiction
Platform: UNKNOWN
Classifier: Development Status :: 3 - Alpha
Classifier: Intended Audience :: Developers
Classifier: Topic :: Education :: Testing
Classifier: License :: OSI Approved :: MIT License
Classifier: Programming Language :: Python :: 3.6
